c3pred/__init__.py
c3pred/c3pred.py
c3pred/cli.py
c3pred/parse_igem_registry.py
c3pred/parsing.py
c3pred/parsing_result.py
c3pred/results.py
c3pred/data/cpp_predictor.sav
c3pred/data/heidiklim.txt
c3pred-0.5.dist-info/AUTHORS.rst
c3pred-0.5.dist-info/LICENSE
c3pred-0.5.dist-info/METADATA
c3pred-0.5.dist-info/WHEEL
c3pred-0.5.dist-info/entry_points.txt
c3pred-0.5.dist-info/top_level.txt
c3pred-0.5.dist-info/RECORD
