Metadata-Version: 2.1
Name: c3pred
Version: 0.5
Summary: Prediction of cargo transport potential of short peptides.
Home-page: https://github.com/steffenlem/c3pred
Author: iGEM Tuebingen
Author-email: info@igem-tuebingen.de
License: MIT license
Keywords: c3pred
Platform: UNKNOWN
Classifier: Development Status :: 2 - Pre-Alpha
Classifier: Intended Audience :: Developers
Classifier: License :: OSI Approved :: MIT License
Classifier: Natural Language :: English
Classifier: Programming Language :: Python :: 3
Classifier: Programming Language :: Python :: 3.5
Classifier: Programming Language :: Python :: 3.6
Classifier: Programming Language :: Python :: 3.7
Requires-Python: !=3.0.*, !=3.1.*, !=3.2.*, !=3.3.*, !=3.4.*
Requires-Dist: click
Requires-Dist: xgboost
Requires-Dist: numpy
Requires-Dist: urllib3
Requires-Dist: xmltodict
Requires-Dist: biopython
